azurecloudhandler/__init__.py
azurecloudhandler/aks/__init__.py
azurecloudhandler/aks/_aks_cmd.py
azurecloudhandler/aks/_aks_operation.py
azurecloudhandler/datalake_gen2/__init__.py
azurecloudhandler/datalake_gen2/_adls2_loads.py
azurecloudhandler-0.3.dist-info/METADATA
azurecloudhandler-0.3.dist-info/WHEEL
azurecloudhandler-0.3.dist-info/top_level.txt
azurecloudhandler-0.3.dist-info/RECORD
