Metadata-Version: 2.1
Name: azurecloudhandler
Version: 0.3
Summary: Library to optimally handle some resources on Azure
Home-page: https://github.com/otacilio-psf/azure-cloud-handler
Author: Otacilio Filho
Author-email: otaciliopedro@gmail.com
License: UNKNOWN
Platform: UNKNOWN
Classifier: Programming Language :: Python :: 3
Classifier: License :: OSI Approved :: MIT License
Classifier: Operating System :: OS Independent
Requires-Dist: azure-identity (>=1.7.1)
Requires-Dist: azure-storage-file-datalake (>=12.5.0)
Requires-Dist: requests (>=2.22.0)
